codethor/__init__.py
codethor/apps/article_writer/articlewriter.py
codethor/apps/contract_generator/index.html
codethor/apps/contract_generator/nda.html
codethor/apps/contract_generator/signature.jpg
codethor/apps/quickintegrate_demo.py
codethor/comments.json
codethor/core.py
codethor/main.py
codethor/output.md
codethor/requirements.txt
codethor/start.ps1
codethor/static/favicon.ico
codethor/static/logo.webp
codethor/terminal.txt
codethor/test/dfinity_parser.py
codethor/test/local_loader.py
codethor/test/math_test.py
codethor/test/ollama_openai.py
codethor/test/ollamabench.py
codethor/test/SamQuickWiki.py
codethor/test/swamix_code_assistant.py
codethor/test/uitest.py
codethor/uaiclient.py
codethor/utils/__init__.py
codethor/utils/emailparser.py
codethor/utils/embedder.py
codethor/utils/scraper.py
codethor/utils/tools.py
codethor-0.1.4.dist-info/METADATA
codethor-0.1.4.dist-info/WHEEL
codethor-0.1.4.dist-info/RECORD
