Metadata-Version: 2.1
Name: codethor
Version: 0.1.4
Summary: An AI enabled highly customizable copilot with agentic capabilities.
Author: M Nikhil Swami
Author-email: nikhilswami1@gmail.com
Requires-Python: >=3.11,<4.0
Classifier: Programming Language :: Python :: 3
Classifier: Programming Language :: Python :: 3.11
Classifier: Programming Language :: Python :: 3.12
Requires-Dist: anthropic (>=0.31.0,<0.32.0)
Requires-Dist: fastapi (>=0.111.0,<0.112.0)
Requires-Dist: ollama (>=0.2.1,<0.3.0)
Requires-Dist: openai (>=1.35.13,<2.0.0)
Requires-Dist: selectolax (>=0.3.21,<0.4.0)
